{
  "project_info": {
    "project_number": "433535746939",
    "firebase_url": "https://tfg-tania.firebaseio.com",
    "project_id": "tfg-tania",
    "storage_bucket": "tfg-tania.appspot.com"
  },
  "client": [
    {
      "client_info": {
        "mobilesdk_app_id": "1:433535746939:android:74f2d6d790edf22c",
        "android_client_info": {
          "package_name": "com.example.tania.aplicaciontfg"
        }
      },
      "oauth_client": [
        {
          "client_id": "433535746939-pa92660e1vgkvc6hlkrjhd9d4eoh3dpa.apps.googleusercontent.com",
          "client_type": 3
        }
      ],
      "api_key": [
        {
          "current_key": "AIzaSyADSf5VhGICL-a7pkU16v26dGQuLaua1dY"
        }
      ],
      "services": {
        "analytics_service": {
          "status": 1
        },
        "appinvite_service": {
          "status": 1,
          "other_platform_oauth_client": []
        },
        "ads_service": {
          "status": 2
        }
      }
    }
  ],
  "configuration_version": "1"
}